greenhack/__init__.py
greenhack/_loop.py
greenhack/as_async.py
greenhack/context_managers.py
greenhack/context_vars.py
greenhack/exempt.py
greenhack/ipy/__init__.py
greenhack/ipy/descriptor.py
greenhack/ipy/runner.py
greenhack/iterators.py
greenhack/start_loop.py
greenhack/utils.py
greenhack-0.1.15.dist-info/WHEEL
greenhack-0.1.15.dist-info/METADATA
greenhack-0.1.15.dist-info/RECORD
